{"cameraMode":{"drawMode":0,"name":"Shaded","section":"Shading Mode"},"sceneLighting":true,"audioPlay":false,"sceneViewState":{"showFog":true,"showMaterialUpdate":false,"showSkybox":true,"showFlares":true,"showImageEffects":true,"showParticleSystems":true},"in2DMode":false,"pivot":{"x":4.235043525695801,"y":-5.228781223297119,"z":15.451725006103516},"rotation":{"x":0.36581501364707949,"y":0.09330443292856217,"z":-0.03688742220401764,"w":0.9252699613571167},"size":25.829044342041017,"orthographic":false}